MISSING_3292/missingval_3292.py
MissingValues_101703292-1.0.3.dist-info/LICENSE.txt
MissingValues_101703292-1.0.3.dist-info/METADATA
MissingValues_101703292-1.0.3.dist-info/WHEEL
MissingValues_101703292-1.0.3.dist-info/entry_points.txt
MissingValues_101703292-1.0.3.dist-info/top_level.txt
MissingValues_101703292-1.0.3.dist-info/RECORD
