Metadata-Version: 2.1
Name: MissingValues-101703292
Version: 1.0.3
Summary: A Python package to handle missing values in the dataset
Home-page: UNKNOWN
Author: Kriti Pandey
Author-email: kritip105@gmail.com
License: MIT
Platform: UNKNOWN
Classifier: License :: OSI Approved :: MIT License
Classifier: Programming Language :: Python :: 3
Classifier: Programming Language :: Python :: 3.7
Requires-Dist: numpy
Requires-Dist: pandas
